CHANGELOG.md
meshlab_pickedpoints/__init__.py
meshlab_pickedpoints/_core.py
meshlab_pickedpoints/cli.py
meshlab_pickedpoints-4.1.0.dist-info/LICENSE
meshlab_pickedpoints-4.1.0.dist-info/WHEEL
meshlab_pickedpoints-4.1.0.dist-info/METADATA
meshlab_pickedpoints-4.1.0.dist-info/RECORD
